{"class":"OpenMetadataArchive","archiveProperties":{"class":"OpenMetadataArchiveProperties","archiveGUID":"2216ab62-176a-46c0-b889-9aa081754b54","archiveName":"SimpleDataCatalog","archiveDescription":"Sample metadata showing data sources and their schemas.","archiveType":"CONTENT_PACK","originatorName":"Egeria","originatorLicense":"Apache 2.0","creationDate":1632046251579,"dependsOnArchives":["bce3b0a0-662a-4f87-b8dc-844078a11a6e"]},"archiveInstanceStore":{"class":"OpenMetadataArchiveInstanceStore","entities":[{"class":"EntityDetail","headerVersion":1,"type":{"class":"InstanceType","headerVersion":1,"typeDefCategory":"ENTITY_DEF","typeDefGUID":"0921c83f-b2db-4086-a52c-0d10e52ca078","typeDefName":"Database","typeDefVersion":2,"typeDefDescription":"A data store containing relational data.","typeDefSuperTypes":[{"headerVersion":1,"guid":"30756d0b-362b-4bfa-a0de-fce6a8f47b47","name":"DataStore","status":"ACTIVE_TYPEDEF"},{"headerVersion":1,"guid":"896d14c2-7522-4f6c-8519-757711943fe6","name":"Asset","status":"ACTIVE_TYPEDEF"},{"headerVersion":1,"guid":"a32316b8-dc8c-48c5-b12b-71c1b2a080bf","name":"Referenceable","status":"ACTIVE_TYPEDEF"},{"headerVersion":1,"guid":"4e7761e8-3969-4627-8f40-bfe3cde85a1d","name":"OpenMetadataRoot","status":"ACTIVE_TYPEDEF"}],"validStatusList":["ACTIVE","DELETED"],"validInstanceProperties":["importedFrom","instance","type","version","databaseVersion","deployedImplementationType","pathName","modifiedTime","storeUpdateTime","createTime","storeCreateTime","owner","ownerType","latestChange","zoneMembership","name","description","qualifiedName","additionalProperties"]},"instanceProvenanceType":"CONTENT_PACK","metadataCollectionId":"2216ab62-176a-46c0-b889-9aa081754b54","createdBy":"Egeria","createTime":1632046251579,"version":1,"guid":"ccdbc02a-f1b0-4ffb-af99-f0bfe7a6ad77","properties":{"class":"InstanceProperties","headerVersion":0,"instanceProperties":{"name":{"class":"PrimitivePropertyValue","headerVersion":0,"instancePropertyCategory":"PRIMITIVE","typeGUID":"b34a64b9-554a-42b1-8f8a-7d5c2339f9c4","typeName":"string","primitiveDefCategory":"OM_PRIMITIVE_TYPE_STRING","primitiveValue":"BRANCH Database"},"description":{"class":"PrimitivePropertyValue","headerVersion":0,"instancePropertyCategory":"PRIMITIVE","typeGUID":"b34a64b9-554a-42b1-8f8a-7d5c2339f9c4","typeName":"string","primitiveDefCategory":"OM_PRIMITIVE_TYPE_STRING","primitiveValue":"Main branch system database."},"qualifiedName":{"class":"PrimitivePropertyValue","headerVersion":0,"instancePropertyCategory":"PRIMITIVE","typeGUID":"b34a64b9-554a-42b1-8f8a-7d5c2339f9c4","typeName":"string","primitiveDefCategory":"OM_PRIMITIVE_TYPE_STRING","primitiveValue":"V37B8752.FH567.sys/BRANCH"}},"propertyCount":3,"propertyNames":["qualifiedName","name","description"]},"status":"ACTIVE"},{"class":"EntityDetail","headerVersion":1,"type":{"class":"InstanceType","headerVersion":1,"typeDefCategory":"ENTITY_DEF","typeDefGUID":"eab811ec-556a-45f1-9091-bc7ac8face0f","typeDefName":"DeployedDatabaseSchema","typeDefVersion":1,"typeDefDescription":"A collection of database tables and views running in a database server.","typeDefSuperTypes":[{"headerVersion":1,"guid":"1449911c-4f44-4c22-abc0-7540154feefb","name":"DataSet","status":"ACTIVE_TYPEDEF"},{"headerVersion":1,"guid":"896d14c2-7522-4f6c-8519-757711943fe6","name":"Asset","status":"ACTIVE_TYPEDEF"},{"headerVersion":1,"guid":"a32316b8-dc8c-48c5-b12b-71c1b2a080bf","name":"Referenceable","status":"ACTIVE_TYPEDEF"},{"headerVersion":1,"guid":"4e7761e8-3969-4627-8f40-bfe3cde85a1d","name":"OpenMetadataRoot","status":"ACTIVE_TYPEDEF"}],"validStatusList":["ACTIVE","DELETED"],"validInstanceProperties":["owner","ownerType","latestChange","zoneMembership","name","description","qualifiedName","additionalProperties"]},"instanceProvenanceType":"CONTENT_PACK","metadataCollectionId":"2216ab62-176a-46c0-b889-9aa081754b54","createdBy":"Egeria","createTime":1632046251579,"version":1,"guid":"f5b75cc8-01b6-45fb-8515-68b798070196","properties":{"class":"InstanceProperties","headerVersion":0,"instanceProperties":{"name":{"class":"PrimitivePropertyValue","headerVersion":0,"instancePropertyCategory":"PRIMITIVE","typeGUID":"b34a64b9-554a-42b1-8f8a-7d5c2339f9c4","typeName":"string","primitiveDefCategory":"OM_PRIMITIVE_TYPE_STRING","primitiveValue":"RETAILSCHEMA"},"description":{"class":"PrimitivePropertyValue","headerVersion":0,"instancePropertyCategory":"PRIMITIVE","typeGUID":"b34a64b9-554a-42b1-8f8a-7d5c2339f9c4","typeName":"string","primitiveDefCategory":"OM_PRIMITIVE_TYPE_STRING","primitiveValue":"Retail banking schema."},"qualifiedName":{"class":"PrimitivePropertyValue","headerVersion":0,"instancePropertyCategory":"PRIMITIVE","typeGUID":"b34a64b9-554a-42b1-8f8a-7d5c2339f9c4","typeName":"string","primitiveDefCategory":"OM_PRIMITIVE_TYPE_STRING","primitiveValue":"V37B8752.FH567.sys/BRANCH.RETAILSCHEMA"}},"propertyCount":3,"propertyNames":["qualifiedName","name","description"]},"status":"ACTIVE"},{"class":"EntityDetail","headerVersion":1,"type":{"class":"InstanceType","headerVersion":1,"typeDefCategory":"ENTITY_DEF","typeDefGUID":"f20f5f45-1afb-41c1-9a09-34d8812626a4","typeDefName":"RelationalDBSchemaType","typeDefVersion":1,"typeDefDescription":"A schema type for a relational database.","typeDefSuperTypes":[{"headerVersion":1,"guid":"786a6199-0ce8-47bf-b006-9ace1c5510e4","name":"ComplexSchemaType","status":"ACTIVE_TYPEDEF"},{"headerVersion":1,"guid":"5bd4a3e7-d22d-4a3d-a115-066ee8e0754f","name":"SchemaType","status":"ACTIVE_TYPEDEF"},{"headerVersion":1,"guid":"718d4244-8559-49ed-ad5a-10e5c305a656","name":"SchemaElement","status":"ACTIVE_TYPEDEF"},{"headerVersion":1,"guid":"a32316b8-dc8c-48c5-b12b-71c1b2a080bf","name":"Referenceable","status":"ACTIVE_TYPEDEF"},{"headerVersion":1,"guid":"4e7761e8-3969-4627-8f40-bfe3cde85a1d","name":"OpenMetadataRoot","status":"ACTIVE_TYPEDEF"}],"validStatusList":["ACTIVE","DELETED"],"validInstanceProperties":["namespace","versionNumber","author","usage","encodingStandard","isDeprecated","displayName","anchorGUID","description","qualifiedName","additionalProperties"]},"instanceProvenanceType":"CONTENT_PACK","metadataCollectionId":"2216ab62-176a-46c0-b889-9aa081754b54","createdBy":"Egeria","createTime":1632046251579,"version":1,"guid":"e3f8b532-ef59-4442-b8ec-19e0a9cb847f","properties":{"class":"InstanceProperties","headerVersion":0,"instanceProperties":{"qualifiedName":{"class":"PrimitivePropertyValue","headerVersion":0,"instancePropertyCategory":"PRIMITIVE","typeGUID":"b34a64b9-554a-42b1-8f8a-7d5c2339f9c4","typeName":"string","primitiveDefCategory":"OM_PRIMITIVE_TYPE_STRING","primitiveValue":"V37B8752.FH567.sys/BRANCH.RETAILSCHEMA_schema_detail"},"displayName":{"class":"PrimitivePropertyValue","headerVersion":0,"instancePropertyCategory":"PRIMITIVE","typeGUID":"b34a64b9-554a-42b1-8f8a-7d5c2339f9c4","typeName":"string","primitiveDefCategory":"OM_PRIMITIVE_TYPE_STRING","primitiveValue":"RETAILSCHEMA Schema Detail"}},"propertyCount":2,"propertyNames":["qualifiedName","displayName"]},"status":"ACTIVE"},{"class":"EntityDetail","headerVersion":1,"type":{"class":"InstanceType","headerVersion":1,"typeDefCategory":"ENTITY_DEF","typeDefGUID":"ce7e72b8-396a-4013-8688-f9d973067425","typeDefName":"RelationalTable","typeDefVersion":1,"typeDefDescription":"A table within a relational database schema type.","typeDefSuperTypes":[{"headerVersion":1,"guid":"1a5e159b-913a-43b1-95fe-04433b25fca9","name":"SchemaAttribute","status":"ACTIVE_TYPEDEF"},{"headerVersion":1,"guid":"718d4244-8559-49ed-ad5a-10e5c305a656","name":"SchemaElement","status":"ACTIVE_TYPEDEF"},{"headerVersion":1,"guid":"a32316b8-dc8c-48c5-b12b-71c1b2a080bf","name":"Referenceable","status":"ACTIVE_TYPEDEF"},{"headerVersion":1,"guid":"4e7761e8-3969-4627-8f40-bfe3cde85a1d","name":"OpenMetadataRoot","status":"ACTIVE_TYPEDEF"}],"validStatusList":["ACTIVE","DELETED"],"validInstanceProperties":["aliases","defaultValueOverride","minimumLength","precision","length","orderedValues","allowsDuplicateValues","significantDigits","maxCardinality","cardinality","minCardinality","nativeClass","sortOrder","isNullable","name","position","isDeprecated","displayName","anchorGUID","description","qualifiedName","additionalProperties"]},"instanceProvenanceType":"CONTENT_PACK","metadataCollectionId":"2216ab62-176a-46c0-b889-9aa081754b54","createdBy":"Egeria","createTime":1632046251579,"version":1,"guid":"46fea469-ba83-496e-859d-963b4ae4101c","classifications":[{"class":"Classification","headerVersion":1,"type":{"class":"InstanceType","headerVersion":1,"typeDefCategory":"CLASSIFICATION_DEF","typeDefGUID":"e2bb76bb-774a-43ff-9045-3a05f663d5d9","typeDefName":"TypeEmbeddedAttribute","typeDefVersion":2,"typeDefDescription":"Type information embedded within an attribute.","validStatusList":["ACTIVE","DELETED"],"validInstanceProperties":["isDeprecated","qualifiedName","displayName","author","defaultValue","dataType","usage","description","schemaTypeName","versionNumber","fixedValue","encodingStandard","additionalProperties"]},"instanceProvenanceType":"CONTENT_PACK","metadataCollectionId":"2216ab62-176a-46c0-b889-9aa081754b54","createdBy":"Egeria","createTime":1632046251579,"version":1,"name":"TypeEmbeddedAttribute","properties":{"class":"InstanceProperties","headerVersion":0,"instanceProperties":{"length":{"class":"PrimitivePropertyValue","headerVersion":0,"instancePropertyCategory":"PRIMITIVE","typeGUID":"7fc49104-fd3a-46c8-b6bf-f16b6074cd35","typeName":"int","primitiveDefCategory":"OM_PRIMITIVE_TYPE_INT","primitiveValue":0},"schemaTypeName":{"class":"PrimitivePropertyValue","headerVersion":0,"instancePropertyCategory":"PRIMITIVE","typeGUID":"b34a64b9-554a-42b1-8f8a-7d5c2339f9c4","typeName":"string","primitiveDefCategory":"OM_PRIMITIVE_TYPE_STRING","primitiveValue":"RelationalTableType"}},"propertyCount":2,"propertyNames":["length","schemaTypeName"]},"status":"ACTIVE"}],"properties":{"class":"InstanceProperties","headerVersion":0,"instanceProperties":{"description":{"class":"PrimitivePropertyValue","headerVersion":0,"instancePropertyCategory":"PRIMITIVE","typeGUID":"b34a64b9-554a-42b1-8f8a-7d5c2339f9c4","typeName":"string","primitiveDefCategory":"OM_PRIMITIVE_TYPE_STRING","primitiveValue":"Branch customer table for retail banking."},"qualifiedName":{"class":"PrimitivePropertyValue","headerVersion":0,"instancePropertyCategory":"PRIMITIVE","typeGUID":"b34a64b9-554a-42b1-8f8a-7d5c2339f9c4","typeName":"string","primitiveDefCategory":"OM_PRIMITIVE_TYPE_STRING","primitiveValue":"V37B8752.FH567.sys/BRANCH.RETAILSCHEMA.CUSTOMER"},"displayName":{"class":"PrimitivePropertyValue","headerVersion":0,"instancePropertyCategory":"PRIMITIVE","typeGUID":"b34a64b9-554a-42b1-8f8a-7d5c2339f9c4","typeName":"string","primitiveDefCategory":"OM_PRIMITIVE_TYPE_STRING","primitiveValue":"CUSTOMER"}},"propertyCount":3,"propertyNames":["qualifiedName","displayName","description"]},"status":"ACTIVE"},{"class":"EntityDetail","headerVersion":1,"type":{"class":"InstanceType","headerVersion":1,"typeDefCategory":"ENTITY_DEF","typeDefGUID":"aa8d5470-6dbc-4648-9e2f-045e5df9d2f9","typeDefName":"RelationalColumn","typeDefVersion":2,"typeDefDescription":"A column within a relational table.","typeDefSuperTypes":[{"headerVersion":1,"guid":"d81a0425-4e9b-4f31-bc1c-e18c3566da10","name":"TabularColumn","status":"ACTIVE_TYPEDEF"},{"headerVersion":1,"guid":"1a5e159b-913a-43b1-95fe-04433b25fca9","name":"SchemaAttribute","status":"ACTIVE_TYPEDEF"},{"headerVersion":1,"guid":"718d4244-8559-49ed-ad5a-10e5c305a656","name":"SchemaElement","status":"ACTIVE_TYPEDEF"},{"headerVersion":1,"guid":"a32316b8-dc8c-48c5-b12b-71c1b2a080bf","name":"Referenceable","status":"ACTIVE_TYPEDEF"},{"headerVersion":1,"guid":"4e7761e8-3969-4627-8f40-bfe3cde85a1d","name":"OpenMetadataRoot","status":"ACTIVE_TYPEDEF"}],"validStatusList":["ACTIVE","DELETED"],"validInstanceProperties":["isUnique","fraction","aliases","defaultValueOverride","minimumLength","precision","length","orderedValues","allowsDuplicateValues","significantDigits","maxCardinality","cardinality","minCardinality","nativeClass","sortOrder","isNullable","name","position","isDeprecated","displayName","anchorGUID","description","qualifiedName","additionalProperties"]},"instanceProvenanceType":"CONTENT_PACK","metadataCollectionId":"2216ab62-176a-46c0-b889-9aa081754b54","createdBy":"Egeria","createTime":1632046251579,"version":1,"guid":"35208ea5-84ff-429c-99c8-0321504a992b","classifications":[{"class":"Classification","headerVersion":1,"type":{"class":"InstanceType","headerVersion":1,"typeDefCategory":"CLASSIFICATION_DEF","typeDefGUID":"e2bb76bb-774a-43ff-9045-3a05f663d5d9","typeDefName":"TypeEmbeddedAttribute","typeDefVersion":2,"typeDefDescription":"Type information embedded within an attribute.","validStatusList":["ACTIVE","DELETED"],"validInstanceProperties":["isDeprecated","qualifiedName","displayName","author","defaultValue","dataType","usage","description","schemaTypeName","versionNumber","fixedValue","encodingStandard","additionalProperties"]},"instanceProvenanceType":"CONTENT_PACK","metadataCollectionId":"2216ab62-176a-46c0-b889-9aa081754b54","createdBy":"Egeria","createTime":1632046251579,"version":1,"name":"TypeEmbeddedAttribute","properties":{"class":"InstanceProperties","headerVersion":0,"instanceProperties":{"length":{"class":"PrimitivePropertyValue","headerVersion":0,"instancePropertyCategory":"PRIMITIVE","typeGUID":"7fc49104-fd3a-46c8-b6bf-f16b6074cd35","typeName":"int","primitiveDefCategory":"OM_PRIMITIVE_TYPE_INT","primitiveValue":12},"schemaTypeName":{"class":"PrimitivePropertyValue","headerVersion":0,"instancePropertyCategory":"PRIMITIVE","typeGUID":"b34a64b9-554a-42b1-8f8a-7d5c2339f9c4","typeName":"string","primitiveDefCategory":"OM_PRIMITIVE_TYPE_STRING","primitiveValue":"PrimitiveSchemaType"},"dataType":{"class":"PrimitivePropertyValue","headerVersion":0,"instancePropertyCategory":"PRIMITIVE","typeGUID":"b34a64b9-554a-42b1-8f8a-7d5c2339f9c4","typeName":"string","primitiveDefCategory":"OM_PRIMITIVE_TYPE_STRING","primitiveValue":"CHAR"}},"propertyCount":3,"propertyNames":["dataType","length","schemaTypeName"]},"status":"ACTIVE"}],"properties":{"class":"InstanceProperties","headerVersion":0,"instanceProperties":{"description":{"class":"PrimitivePropertyValue","headerVersion":0,"instancePropertyCategory":"PRIMITIVE","typeGUID":"b34a64b9-554a-42b1-8f8a-7d5c2339f9c4","typeName":"string","primitiveDefCategory":"OM_PRIMITIVE_TYPE_STRING","primitiveValue":"The unique identifier assigned internally for a customer."},"qualifiedName":{"class":"PrimitivePropertyValue","headerVersion":0,"instancePropertyCategory":"PRIMITIVE","typeGUID":"b34a64b9-554a-42b1-8f8a-7d5c2339f9c4","typeName":"string","primitiveDefCategory":"OM_PRIMITIVE_TYPE_STRING","primitiveValue":"V37B8752.FH567.sys/BRANCH.RETAILSCHEMA.CUSTOMER.CUSTID"},"displayName":{"class":"PrimitivePropertyValue","headerVersion":0,"instancePropertyCategory":"PRIMITIVE","typeGUID":"b34a64b9-554a-42b1-8f8a-7d5c2339f9c4","typeName":"string","primitiveDefCategory":"OM_PRIMITIVE_TYPE_STRING","primitiveValue":"CUSTID"}},"propertyCount":3,"propertyNames":["qualifiedName","displayName","description"]},"status":"ACTIVE"},{"class":"EntityDetail","headerVersion":1,"type":{"class":"InstanceType","headerVersion":1,"typeDefCategory":"ENTITY_DEF","typeDefGUID":"aa8d5470-6dbc-4648-9e2f-045e5df9d2f9","typeDefName":"RelationalColumn","typeDefVersion":2,"typeDefDescription":"A column within a relational table.","typeDefSuperTypes":[{"headerVersion":1,"guid":"d81a0425-4e9b-4f31-bc1c-e18c3566da10","name":"TabularColumn","status":"ACTIVE_TYPEDEF"},{"headerVersion":1,"guid":"1a5e159b-913a-43b1-95fe-04433b25fca9","name":"SchemaAttribute","status":"ACTIVE_TYPEDEF"},{"headerVersion":1,"guid":"718d4244-8559-49ed-ad5a-10e5c305a656","name":"SchemaElement","status":"ACTIVE_TYPEDEF"},{"headerVersion":1,"guid":"a32316b8-dc8c-48c5-b12b-71c1b2a080bf","name":"Referenceable","status":"ACTIVE_TYPEDEF"},{"headerVersion":1,"guid":"4e7761e8-3969-4627-8f40-bfe3cde85a1d","name":"OpenMetadataRoot","status":"ACTIVE_TYPEDEF"}],"validStatusList":["ACTIVE","DELETED"],"validInstanceProperties":["isUnique","fraction","aliases","defaultValueOverride","minimumLength","precision","length","orderedValues","allowsDuplicateValues","significantDigits","maxCardinality","cardinality","minCardinality","nativeClass","sortOrder","isNullable","name","position","isDeprecated","displayName","anchorGUID","description","qualifiedName","additionalProperties"]},"instanceProvenanceType":"CONTENT_PACK","metadataCollectionId":"2216ab62-176a-46c0-b889-9aa081754b54","createdBy":"Egeria","createTime":1632046251579,"version":1,"guid":"95395f0d-cf4d-4c05-be42-908931b1d470","classifications":[{"class":"Classification","headerVersion":1,"type":{"class":"InstanceType","headerVersion":1,"typeDefCategory":"CLASSIFICATION_DEF","typeDefGUID":"e2bb76bb-774a-43ff-9045-3a05f663d5d9","typeDefName":"TypeEmbeddedAttribute","typeDefVersion":2,"typeDefDescription":"Type information embedded within an attribute.","validStatusList":["ACTIVE","DELETED"],"validInstanceProperties":["isDeprecated","qualifiedName","displayName","author","defaultValue","dataType","usage","description","schemaTypeName","versionNumber","fixedValue","encodingStandard","additionalProperties"]},"instanceProvenanceType":"CONTENT_PACK","metadataCollectionId":"2216ab62-176a-46c0-b889-9aa081754b54","createdBy":"Egeria","createTime":1632046251579,"version":1,"name":"TypeEmbeddedAttribute","properties":{"class":"InstanceProperties","headerVersion":0,"instanceProperties":{"length":{"class":"PrimitivePropertyValue","headerVersion":0,"instancePropertyCategory":"PRIMITIVE","typeGUID":"7fc49104-fd3a-46c8-b6bf-f16b6074cd35","typeName":"int","primitiveDefCategory":"OM_PRIMITIVE_TYPE_INT","primitiveValue":40},"schemaTypeName":{"class":"PrimitivePropertyValue","headerVersion":0,"instancePropertyCategory":"PRIMITIVE","typeGUID":"b34a64b9-554a-42b1-8f8a-7d5c2339f9c4","typeName":"string","primitiveDefCategory":"OM_PRIMITIVE_TYPE_STRING","primitiveValue":"PrimitiveSchemaType"},"dataType":{"class":"PrimitivePropertyValue","headerVersion":0,"instancePropertyCategory":"PRIMITIVE","typeGUID":"b34a64b9-554a-42b1-8f8a-7d5c2339f9c4","typeName":"string","primitiveDefCategory":"OM_PRIMITIVE_TYPE_STRING","primitiveValue":"CHAR"}},"propertyCount":3,"propertyNames":["dataType","length","schemaTypeName"]},"status":"ACTIVE"}],"properties":{"class":"InstanceProperties","headerVersion":0,"instanceProperties":{"description":{"class":"PrimitivePropertyValue","headerVersion":0,"instancePropertyCategory":"PRIMITIVE","typeGUID":"b34a64b9-554a-42b1-8f8a-7d5c2339f9c4","typeName":"string","primitiveDefCategory":"OM_PRIMITIVE_TYPE_STRING","primitiveValue":"The name for a customer - as supplied by the customer."},"qualifiedName":{"class":"PrimitivePropertyValue","headerVersion":0,"instancePropertyCategory":"PRIMITIVE","typeGUID":"b34a64b9-554a-42b1-8f8a-7d5c2339f9c4","typeName":"string","primitiveDefCategory":"OM_PRIMITIVE_TYPE_STRING","primitiveValue":"V37B8752.FH567.sys/BRANCH.RETAILSCHEMA.CUSTOMER.CUSTNAME"},"displayName":{"class":"PrimitivePropertyValue","headerVersion":0,"instancePropertyCategory":"PRIMITIVE","typeGUID":"b34a64b9-554a-42b1-8f8a-7d5c2339f9c4","typeName":"string","primitiveDefCategory":"OM_PRIMITIVE_TYPE_STRING","primitiveValue":"CUSTNAME"}},"propertyCount":3,"propertyNames":["qualifiedName","displayName","description"]},"status":"ACTIVE"},{"class":"EntityDetail","headerVersion":1,"type":{"class":"InstanceType","headerVersion":1,"typeDefCategory":"ENTITY_DEF","typeDefGUID":"aa8d5470-6dbc-4648-9e2f-045e5df9d2f9","typeDefName":"RelationalColumn","typeDefVersion":2,"typeDefDescription":"A column within a relational table.","typeDefSuperTypes":[{"headerVersion":1,"guid":"d81a0425-4e9b-4f31-bc1c-e18c3566da10","name":"TabularColumn","status":"ACTIVE_TYPEDEF"},{"headerVersion":1,"guid":"1a5e159b-913a-43b1-95fe-04433b25fca9","name":"SchemaAttribute","status":"ACTIVE_TYPEDEF"},{"headerVersion":1,"guid":"718d4244-8559-49ed-ad5a-10e5c305a656","name":"SchemaElement","status":"ACTIVE_TYPEDEF"},{"headerVersion":1,"guid":"a32316b8-dc8c-48c5-b12b-71c1b2a080bf","name":"Referenceable","status":"ACTIVE_TYPEDEF"},{"headerVersion":1,"guid":"4e7761e8-3969-4627-8f40-bfe3cde85a1d","name":"OpenMetadataRoot","status":"ACTIVE_TYPEDEF"}],"validStatusList":["ACTIVE","DELETED"],"validInstanceProperties":["isUnique","fraction","aliases","defaultValueOverride","minimumLength","precision","length","orderedValues","allowsDuplicateValues","significantDigits","maxCardinality","cardinality","minCardinality","nativeClass","sortOrder","isNullable","name","position","isDeprecated","displayName","anchorGUID","description","qualifiedName","additionalProperties"]},"instanceProvenanceType":"CONTENT_PACK","metadataCollectionId":"2216ab62-176a-46c0-b889-9aa081754b54","createdBy":"Egeria","createTime":1632046251579,"version":1,"guid":"b3bfe44e-5b40-4c7a-b770-4b9f8f4be9b3","classifications":[{"class":"Classification","headerVersion":1,"type":{"class":"InstanceType","headerVersion":1,"typeDefCategory":"CLASSIFICATION_DEF","typeDefGUID":"e2bb76bb-774a-43ff-9045-3a05f663d5d9","typeDefName":"TypeEmbeddedAttribute","typeDefVersion":2,"typeDefDescription":"Type information embedded within an attribute.","validStatusList":["ACTIVE","DELETED"],"validInstanceProperties":["isDeprecated","qualifiedName","displayName","author","defaultValue","dataType","usage","description","schemaTypeName","versionNumber","fixedValue","encodingStandard","additionalProperties"]},"instanceProvenanceType":"CONTENT_PACK","metadataCollectionId":"2216ab62-176a-46c0-b889-9aa081754b54","createdBy":"Egeria","createTime":1632046251579,"version":1,"name":"TypeEmbeddedAttribute","properties":{"class":"InstanceProperties","headerVersion":0,"instanceProperties":{"length":{"class":"PrimitivePropertyValue","headerVersion":0,"instancePropertyCategory":"PRIMITIVE","typeGUID":"7fc49104-fd3a-46c8-b6bf-f16b6074cd35","typeName":"int","primitiveDefCategory":"OM_PRIMITIVE_TYPE_INT","primitiveValue":10},"schemaTypeName":{"class":"PrimitivePropertyValue","headerVersion":0,"instancePropertyCategory":"PRIMITIVE","typeGUID":"b34a64b9-554a-42b1-8f8a-7d5c2339f9c4","typeName":"string","primitiveDefCategory":"OM_PRIMITIVE_TYPE_STRING","primitiveValue":"PrimitiveSchemaType"},"dataType":{"class":"PrimitivePropertyValue","headerVersion":0,"instancePropertyCategory":"PRIMITIVE","typeGUID":"b34a64b9-554a-42b1-8f8a-7d5c2339f9c4","typeName":"string","primitiveDefCategory":"OM_PRIMITIVE_TYPE_STRING","primitiveValue":"CHAR"}},"propertyCount":3,"propertyNames":["dataType","length","schemaTypeName"]},"status":"ACTIVE"}],"properties":{"class":"InstanceProperties","headerVersion":0,"instanceProperties":{"description":{"class":"PrimitivePropertyValue","headerVersion":0,"instancePropertyCategory":"PRIMITIVE","typeGUID":"b34a64b9-554a-42b1-8f8a-7d5c2339f9c4","typeName":"string","primitiveDefCategory":"OM_PRIMITIVE_TYPE_STRING","primitiveValue":"The calculated status for a customer indicating their value to the organization."},"qualifiedName":{"class":"PrimitivePropertyValue","headerVersion":0,"instancePropertyCategory":"PRIMITIVE","typeGUID":"b34a64b9-554a-42b1-8f8a-7d5c2339f9c4","typeName":"string","primitiveDefCategory":"OM_PRIMITIVE_TYPE_STRING","primitiveValue":"V37B8752.FH567.sys/BRANCH.RETAILSCHEMA.CUSTOMER.CUSTSTATUS"},"displayName":{"class":"PrimitivePropertyValue","headerVersion":0,"instancePropertyCategory":"PRIMITIVE","typeGUID":"b34a64b9-554a-42b1-8f8a-7d5c2339f9c4","typeName":"string","primitiveDefCategory":"OM_PRIMITIVE_TYPE_STRING","primitiveValue":"CUSTSTATUS"}},"propertyCount":3,"propertyNames":["qualifiedName","displayName","description"]},"status":"ACTIVE"},{"class":"EntityDetail","headerVersion":1,"type":{"class":"InstanceType","headerVersion":1,"typeDefCategory":"ENTITY_DEF","typeDefGUID":"aa8d5470-6dbc-4648-9e2f-045e5df9d2f9","typeDefName":"RelationalColumn","typeDefVersion":2,"typeDefDescription":"A column within a relational table.","typeDefSuperTypes":[{"headerVersion":1,"guid":"d81a0425-4e9b-4f31-bc1c-e18c3566da10","name":"TabularColumn","status":"ACTIVE_TYPEDEF"},{"headerVersion":1,"guid":"1a5e159b-913a-43b1-95fe-04433b25fca9","name":"SchemaAttribute","status":"ACTIVE_TYPEDEF"},{"headerVersion":1,"guid":"718d4244-8559-49ed-ad5a-10e5c305a656","name":"SchemaElement","status":"ACTIVE_TYPEDEF"},{"headerVersion":1,"guid":"a32316b8-dc8c-48c5-b12b-71c1b2a080bf","name":"Referenceable","status":"ACTIVE_TYPEDEF"},{"headerVersion":1,"guid":"4e7761e8-3969-4627-8f40-bfe3cde85a1d","name":"OpenMetadataRoot","status":"ACTIVE_TYPEDEF"}],"validStatusList":["ACTIVE","DELETED"],"validInstanceProperties":["isUnique","fraction","aliases","defaultValueOverride","minimumLength","precision","length","orderedValues","allowsDuplicateValues","significantDigits","maxCardinality","cardinality","minCardinality","nativeClass","sortOrder","isNullable","name","position","isDeprecated","displayName","anchorGUID","description","qualifiedName","additionalProperties"]},"instanceProvenanceType":"CONTENT_PACK","metadataCollectionId":"2216ab62-176a-46c0-b889-9aa081754b54","createdBy":"Egeria","createTime":1632046251579,"version":1,"guid":"acfcae4c-f1a8-42dc-ac7d-28e56516721c","classifications":[{"class":"Classification","headerVersion":1,"type":{"class":"InstanceType","headerVersion":1,"typeDefCategory":"CLASSIFICATION_DEF","typeDefGUID":"e2bb76bb-774a-43ff-9045-3a05f663d5d9","typeDefName":"TypeEmbeddedAttribute","typeDefVersion":2,"typeDefDescription":"Type information embedded within an attribute.","validStatusList":["ACTIVE","DELETED"],"validInstanceProperties":["isDeprecated","qualifiedName","displayName","author","defaultValue","dataType","usage","description","schemaTypeName","versionNumber","fixedValue","encodingStandard","additionalProperties"]},"instanceProvenanceType":"CONTENT_PACK","metadataCollectionId":"2216ab62-176a-46c0-b889-9aa081754b54","createdBy":"Egeria","createTime":1632046251579,"version":1,"name":"TypeEmbeddedAttribute","properties":{"class":"InstanceProperties","headerVersion":0,"instanceProperties":{"length":{"class":"PrimitivePropertyValue","headerVersion":0,"instancePropertyCategory":"PRIMITIVE","typeGUID":"7fc49104-fd3a-46c8-b6bf-f16b6074cd35","typeName":"int","primitiveDefCategory":"OM_PRIMITIVE_TYPE_INT","primitiveValue":10},"schemaTypeName":{"class":"PrimitivePropertyValue","headerVersion":0,"instancePropertyCategory":"PRIMITIVE","typeGUID":"b34a64b9-554a-42b1-8f8a-7d5c2339f9c4","typeName":"string","primitiveDefCategory":"OM_PRIMITIVE_TYPE_STRING","primitiveValue":"PrimitiveSchemaType"},"dataType":{"class":"PrimitivePropertyValue","headerVersion":0,"instancePropertyCategory":"PRIMITIVE","typeGUID":"b34a64b9-554a-42b1-8f8a-7d5c2339f9c4","typeName":"string","primitiveDefCategory":"OM_PRIMITIVE_TYPE_STRING","primitiveValue":"CHAR"}},"propertyCount":3,"propertyNames":["dataType","length","schemaTypeName"]},"status":"ACTIVE"}],"properties":{"class":"InstanceProperties","headerVersion":0,"instanceProperties":{"description":{"class":"PrimitivePropertyValue","headerVersion":0,"instancePropertyCategory":"PRIMITIVE","typeGUID":"b34a64b9-554a-42b1-8f8a-7d5c2339f9c4","typeName":"string","primitiveDefCategory":"OM_PRIMITIVE_TYPE_STRING","primitiveValue":"The store card number for the customer.  Null if not issued."},"qualifiedName":{"class":"PrimitivePropertyValue","headerVersion":0,"instancePropertyCategory":"PRIMITIVE","typeGUID":"b34a64b9-554a-42b1-8f8a-7d5c2339f9c4","typeName":"string","primitiveDefCategory":"OM_PRIMITIVE_TYPE_STRING","primitiveValue":"V37B8752.FH567.sys/BRANCH.RETAILSCHEMA.CUSTOMER.CUSTCARD"},"displayName":{"class":"PrimitivePropertyValue","headerVersion":0,"instancePropertyCategory":"PRIMITIVE","typeGUID":"b34a64b9-554a-42b1-8f8a-7d5c2339f9c4","typeName":"string","primitiveDefCategory":"OM_PRIMITIVE_TYPE_STRING","primitiveValue":"CUSTCARD"}},"propertyCount":3,"propertyNames":["qualifiedName","displayName","description"]},"status":"ACTIVE"}],"relationships":[{"class":"Relationship","headerVersion":1,"type":{"class":"InstanceType","headerVersion":1,"typeDefCategory":"RELATIONSHIP_DEF","typeDefGUID":"b827683c-2924-4df3-a92d-7be1888e23c0","typeDefName":"DataContentForDataSet","typeDefVersion":1,"typeDefDescription":"The assets that provides data for a data set.","validStatusList":["ACTIVE","DELETED"]},"instanceProvenanceType":"CONTENT_PACK","metadataCollectionId":"2216ab62-176a-46c0-b889-9aa081754b54","createdBy":"Egeria","createTime":1632046251579,"version":1,"guid":"2fb3ed27-34e4-449b-966c-6d6ff351edf2","entityOneProxy":{"class":"EntityProxy","headerVersion":1,"type":{"class":"InstanceType","headerVersion":1,"typeDefCategory":"ENTITY_DEF","typeDefGUID":"0921c83f-b2db-4086-a52c-0d10e52ca078","typeDefName":"Database","typeDefVersion":2,"typeDefDescription":"A data store containing relational data.","typeDefSuperTypes":[{"headerVersion":1,"guid":"30756d0b-362b-4bfa-a0de-fce6a8f47b47","name":"DataStore","status":"ACTIVE_TYPEDEF"},{"headerVersion":1,"guid":"896d14c2-7522-4f6c-8519-757711943fe6","name":"Asset","status":"ACTIVE_TYPEDEF"},{"headerVersion":1,"guid":"a32316b8-dc8c-48c5-b12b-71c1b2a080bf","name":"Referenceable","status":"ACTIVE_TYPEDEF"},{"headerVersion":1,"guid":"4e7761e8-3969-4627-8f40-bfe3cde85a1d","name":"OpenMetadataRoot","status":"ACTIVE_TYPEDEF"}],"validStatusList":["ACTIVE","DELETED"],"validInstanceProperties":["importedFrom","instance","type","version","databaseVersion","deployedImplementationType","pathName","modifiedTime","storeUpdateTime","createTime","storeCreateTime","owner","ownerType","latestChange","zoneMembership","name","description","qualifiedName","additionalProperties"]},"instanceProvenanceType":"CONTENT_PACK","metadataCollectionId":"2216ab62-176a-46c0-b889-9aa081754b54","createdBy":"Egeria","createTime":1632046251579,"version":1,"guid":"ccdbc02a-f1b0-4ffb-af99-f0bfe7a6ad77","uniqueProperties":{"class":"InstanceProperties","headerVersion":0,"instanceProperties":{"qualifiedName":{"class":"PrimitivePropertyValue","headerVersion":0,"instancePropertyCategory":"PRIMITIVE","typeGUID":"b34a64b9-554a-42b1-8f8a-7d5c2339f9c4","typeName":"string","primitiveDefCategory":"OM_PRIMITIVE_TYPE_STRING","primitiveValue":"V37B8752.FH567.sys/BRANCH"}},"propertyCount":1,"propertyNames":["qualifiedName"]},"status":"ACTIVE"},"entityTwoProxy":{"class":"EntityProxy","headerVersion":1,"type":{"class":"InstanceType","headerVersion":1,"typeDefCategory":"ENTITY_DEF","typeDefGUID":"eab811ec-556a-45f1-9091-bc7ac8face0f","typeDefName":"DeployedDatabaseSchema","typeDefVersion":1,"typeDefDescription":"A collection of database tables and views running in a database server.","typeDefSuperTypes":[{"headerVersion":1,"guid":"1449911c-4f44-4c22-abc0-7540154feefb","name":"DataSet","status":"ACTIVE_TYPEDEF"},{"headerVersion":1,"guid":"896d14c2-7522-4f6c-8519-757711943fe6","name":"Asset","status":"ACTIVE_TYPEDEF"},{"headerVersion":1,"guid":"a32316b8-dc8c-48c5-b12b-71c1b2a080bf","name":"Referenceable","status":"ACTIVE_TYPEDEF"},{"headerVersion":1,"guid":"4e7761e8-3969-4627-8f40-bfe3cde85a1d","name":"OpenMetadataRoot","status":"ACTIVE_TYPEDEF"}],"validStatusList":["ACTIVE","DELETED"],"validInstanceProperties":["owner","ownerType","latestChange","zoneMembership","name","description","qualifiedName","additionalProperties"]},"instanceProvenanceType":"CONTENT_PACK","metadataCollectionId":"2216ab62-176a-46c0-b889-9aa081754b54","createdBy":"Egeria","createTime":1632046251579,"version":1,"guid":"f5b75cc8-01b6-45fb-8515-68b798070196","uniqueProperties":{"class":"InstanceProperties","headerVersion":0,"instanceProperties":{"qualifiedName":{"class":"PrimitivePropertyValue","headerVersion":0,"instancePropertyCategory":"PRIMITIVE","typeGUID":"b34a64b9-554a-42b1-8f8a-7d5c2339f9c4","typeName":"string","primitiveDefCategory":"OM_PRIMITIVE_TYPE_STRING","primitiveValue":"V37B8752.FH567.sys/BRANCH.RETAILSCHEMA"}},"propertyCount":1,"propertyNames":["qualifiedName"]},"status":"ACTIVE"},"status":"ACTIVE"},{"class":"Relationship","headerVersion":1,"type":{"class":"InstanceType","headerVersion":1,"typeDefCategory":"RELATIONSHIP_DEF","typeDefGUID":"815b004d-73c6-4728-9dd9-536f4fe803cd","typeDefName":"AssetSchemaType","typeDefVersion":1,"typeDefDescription":"The structure of an asset.","validStatusList":["ACTIVE","DELETED"]},"instanceProvenanceType":"CONTENT_PACK","metadataCollectionId":"2216ab62-176a-46c0-b889-9aa081754b54","createdBy":"Egeria","createTime":1632046251579,"version":1,"guid":"3d04d667-5362-46e3-98d9-182ddefa0d07","entityOneProxy":{"class":"EntityProxy","headerVersion":1,"type":{"class":"InstanceType","headerVersion":1,"typeDefCategory":"ENTITY_DEF","typeDefGUID":"eab811ec-556a-45f1-9091-bc7ac8face0f","typeDefName":"DeployedDatabaseSchema","typeDefVersion":1,"typeDefDescription":"A collection of database tables and views running in a database server.","typeDefSuperTypes":[{"headerVersion":1,"guid":"1449911c-4f44-4c22-abc0-7540154feefb","name":"DataSet","status":"ACTIVE_TYPEDEF"},{"headerVersion":1,"guid":"896d14c2-7522-4f6c-8519-757711943fe6","name":"Asset","status":"ACTIVE_TYPEDEF"},{"headerVersion":1,"guid":"a32316b8-dc8c-48c5-b12b-71c1b2a080bf","name":"Referenceable","status":"ACTIVE_TYPEDEF"},{"headerVersion":1,"guid":"4e7761e8-3969-4627-8f40-bfe3cde85a1d","name":"OpenMetadataRoot","status":"ACTIVE_TYPEDEF"}],"validStatusList":["ACTIVE","DELETED"],"validInstanceProperties":["owner","ownerType","latestChange","zoneMembership","name","description","qualifiedName","additionalProperties"]},"instanceProvenanceType":"CONTENT_PACK","metadataCollectionId":"2216ab62-176a-46c0-b889-9aa081754b54","createdBy":"Egeria","createTime":1632046251579,"version":1,"guid":"f5b75cc8-01b6-45fb-8515-68b798070196","uniqueProperties":{"class":"InstanceProperties","headerVersion":0,"instanceProperties":{"qualifiedName":{"class":"PrimitivePropertyValue","headerVersion":0,"instancePropertyCategory":"PRIMITIVE","typeGUID":"b34a64b9-554a-42b1-8f8a-7d5c2339f9c4","typeName":"string","primitiveDefCategory":"OM_PRIMITIVE_TYPE_STRING","primitiveValue":"V37B8752.FH567.sys/BRANCH.RETAILSCHEMA"}},"propertyCount":1,"propertyNames":["qualifiedName"]},"status":"ACTIVE"},"entityTwoProxy":{"class":"EntityProxy","headerVersion":1,"type":{"class":"InstanceType","headerVersion":1,"typeDefCategory":"ENTITY_DEF","typeDefGUID":"f20f5f45-1afb-41c1-9a09-34d8812626a4","typeDefName":"RelationalDBSchemaType","typeDefVersion":1,"typeDefDescription":"A schema type for a relational database.","typeDefSuperTypes":[{"headerVersion":1,"guid":"786a6199-0ce8-47bf-b006-9ace1c5510e4","name":"ComplexSchemaType","status":"ACTIVE_TYPEDEF"},{"headerVersion":1,"guid":"5bd4a3e7-d22d-4a3d-a115-066ee8e0754f","name":"SchemaType","status":"ACTIVE_TYPEDEF"},{"headerVersion":1,"guid":"718d4244-8559-49ed-ad5a-10e5c305a656","name":"SchemaElement","status":"ACTIVE_TYPEDEF"},{"headerVersion":1,"guid":"a32316b8-dc8c-48c5-b12b-71c1b2a080bf","name":"Referenceable","status":"ACTIVE_TYPEDEF"},{"headerVersion":1,"guid":"4e7761e8-3969-4627-8f40-bfe3cde85a1d","name":"OpenMetadataRoot","status":"ACTIVE_TYPEDEF"}],"validStatusList":["ACTIVE","DELETED"],"validInstanceProperties":["namespace","versionNumber","author","usage","encodingStandard","isDeprecated","displayName","anchorGUID","description","qualifiedName","additionalProperties"]},"instanceProvenanceType":"CONTENT_PACK","metadataCollectionId":"2216ab62-176a-46c0-b889-9aa081754b54","createdBy":"Egeria","createTime":1632046251579,"version":1,"guid":"e3f8b532-ef59-4442-b8ec-19e0a9cb847f","uniqueProperties":{"class":"InstanceProperties","headerVersion":0,"instanceProperties":{"qualifiedName":{"class":"PrimitivePropertyValue","headerVersion":0,"instancePropertyCategory":"PRIMITIVE","typeGUID":"b34a64b9-554a-42b1-8f8a-7d5c2339f9c4","typeName":"string","primitiveDefCategory":"OM_PRIMITIVE_TYPE_STRING","primitiveValue":"V37B8752.FH567.sys/BRANCH.RETAILSCHEMA_schema_detail"}},"propertyCount":1,"propertyNames":["qualifiedName"]},"status":"ACTIVE"},"status":"ACTIVE"},{"class":"Relationship","headerVersion":1,"type":{"class":"InstanceType","headerVersion":1,"typeDefCategory":"RELATIONSHIP_DEF","typeDefGUID":"86b176a2-015c-44a6-8106-54d5d69ba661","typeDefName":"AttributeForSchema","typeDefVersion":1,"typeDefDescription":"Link between a complex schema type and its attributes.","validStatusList":["ACTIVE","DELETED"]},"instanceProvenanceType":"CONTENT_PACK","metadataCollectionId":"2216ab62-176a-46c0-b889-9aa081754b54","createdBy":"Egeria","createTime":1632046251579,"version":1,"guid":"b6a17a5c-ebed-4f2f-b1da-0f9390c096ab","entityOneProxy":{"class":"EntityProxy","headerVersion":1,"type":{"class":"InstanceType","headerVersion":1,"typeDefCategory":"ENTITY_DEF","typeDefGUID":"f20f5f45-1afb-41c1-9a09-34d8812626a4","typeDefName":"RelationalDBSchemaType","typeDefVersion":1,"typeDefDescription":"A schema type for a relational database.","typeDefSuperTypes":[{"headerVersion":1,"guid":"786a6199-0ce8-47bf-b006-9ace1c5510e4","name":"ComplexSchemaType","status":"ACTIVE_TYPEDEF"},{"headerVersion":1,"guid":"5bd4a3e7-d22d-4a3d-a115-066ee8e0754f","name":"SchemaType","status":"ACTIVE_TYPEDEF"},{"headerVersion":1,"guid":"718d4244-8559-49ed-ad5a-10e5c305a656","name":"SchemaElement","status":"ACTIVE_TYPEDEF"},{"headerVersion":1,"guid":"a32316b8-dc8c-48c5-b12b-71c1b2a080bf","name":"Referenceable","status":"ACTIVE_TYPEDEF"},{"headerVersion":1,"guid":"4e7761e8-3969-4627-8f40-bfe3cde85a1d","name":"OpenMetadataRoot","status":"ACTIVE_TYPEDEF"}],"validStatusList":["ACTIVE","DELETED"],"validInstanceProperties":["namespace","versionNumber","author","usage","encodingStandard","isDeprecated","displayName","anchorGUID","description","qualifiedName","additionalProperties"]},"instanceProvenanceType":"CONTENT_PACK","metadataCollectionId":"2216ab62-176a-46c0-b889-9aa081754b54","createdBy":"Egeria","createTime":1632046251579,"version":1,"guid":"e3f8b532-ef59-4442-b8ec-19e0a9cb847f","uniqueProperties":{"class":"InstanceProperties","headerVersion":0,"instanceProperties":{"qualifiedName":{"class":"PrimitivePropertyValue","headerVersion":0,"instancePropertyCategory":"PRIMITIVE","typeGUID":"b34a64b9-554a-42b1-8f8a-7d5c2339f9c4","typeName":"string","primitiveDefCategory":"OM_PRIMITIVE_TYPE_STRING","primitiveValue":"V37B8752.FH567.sys/BRANCH.RETAILSCHEMA_schema_detail"}},"propertyCount":1,"propertyNames":["qualifiedName"]},"status":"ACTIVE"},"entityTwoProxy":{"class":"EntityProxy","headerVersion":1,"type":{"class":"InstanceType","headerVersion":1,"typeDefCategory":"ENTITY_DEF","typeDefGUID":"ce7e72b8-396a-4013-8688-f9d973067425","typeDefName":"RelationalTable","typeDefVersion":1,"typeDefDescription":"A table within a relational database schema type.","typeDefSuperTypes":[{"headerVersion":1,"guid":"1a5e159b-913a-43b1-95fe-04433b25fca9","name":"SchemaAttribute","status":"ACTIVE_TYPEDEF"},{"headerVersion":1,"guid":"718d4244-8559-49ed-ad5a-10e5c305a656","name":"SchemaElement","status":"ACTIVE_TYPEDEF"},{"headerVersion":1,"guid":"a32316b8-dc8c-48c5-b12b-71c1b2a080bf","name":"Referenceable","status":"ACTIVE_TYPEDEF"},{"headerVersion":1,"guid":"4e7761e8-3969-4627-8f40-bfe3cde85a1d","name":"OpenMetadataRoot","status":"ACTIVE_TYPEDEF"}],"validStatusList":["ACTIVE","DELETED"],"validInstanceProperties":["aliases","defaultValueOverride","minimumLength","precision","length","orderedValues","allowsDuplicateValues","significantDigits","maxCardinality","cardinality","minCardinality","nativeClass","sortOrder","isNullable","name","position","isDeprecated","displayName","anchorGUID","description","qualifiedName","additionalProperties"]},"instanceProvenanceType":"CONTENT_PACK","metadataCollectionId":"2216ab62-176a-46c0-b889-9aa081754b54","createdBy":"Egeria","createTime":1632046251579,"version":1,"guid":"46fea469-ba83-496e-859d-963b4ae4101c","classifications":[{"class":"Classification","headerVersion":1,"type":{"class":"InstanceType","headerVersion":1,"typeDefCategory":"CLASSIFICATION_DEF","typeDefGUID":"e2bb76bb-774a-43ff-9045-3a05f663d5d9","typeDefName":"TypeEmbeddedAttribute","typeDefVersion":2,"typeDefDescription":"Type information embedded within an attribute.","validStatusList":["ACTIVE","DELETED"],"validInstanceProperties":["isDeprecated","qualifiedName","displayName","author","defaultValue","dataType","usage","description","schemaTypeName","versionNumber","fixedValue","encodingStandard","additionalProperties"]},"instanceProvenanceType":"CONTENT_PACK","metadataCollectionId":"2216ab62-176a-46c0-b889-9aa081754b54","createdBy":"Egeria","createTime":1632046251579,"version":1,"name":"TypeEmbeddedAttribute","properties":{"class":"InstanceProperties","headerVersion":0,"instanceProperties":{"length":{"class":"PrimitivePropertyValue","headerVersion":0,"instancePropertyCategory":"PRIMITIVE","typeGUID":"7fc49104-fd3a-46c8-b6bf-f16b6074cd35","typeName":"int","primitiveDefCategory":"OM_PRIMITIVE_TYPE_INT","primitiveValue":0},"schemaTypeName":{"class":"PrimitivePropertyValue","headerVersion":0,"instancePropertyCategory":"PRIMITIVE","typeGUID":"b34a64b9-554a-42b1-8f8a-7d5c2339f9c4","typeName":"string","primitiveDefCategory":"OM_PRIMITIVE_TYPE_STRING","primitiveValue":"RelationalTableType"}},"propertyCount":2,"propertyNames":["length","schemaTypeName"]},"status":"ACTIVE"}],"uniqueProperties":{"class":"InstanceProperties","headerVersion":0,"instanceProperties":{"qualifiedName":{"class":"PrimitivePropertyValue","headerVersion":0,"instancePropertyCategory":"PRIMITIVE","typeGUID":"b34a64b9-554a-42b1-8f8a-7d5c2339f9c4","typeName":"string","primitiveDefCategory":"OM_PRIMITIVE_TYPE_STRING","primitiveValue":"V37B8752.FH567.sys/BRANCH.RETAILSCHEMA.CUSTOMER"}},"propertyCount":1,"propertyNames":["qualifiedName"]},"status":"ACTIVE"},"status":"ACTIVE"},{"class":"Relationship","headerVersion":1,"type":{"class":"InstanceType","headerVersion":1,"typeDefCategory":"RELATIONSHIP_DEF","typeDefGUID":"0ffb9d87-7074-45da-a9b0-ae0859611133","typeDefName":"NestedSchemaAttribute","typeDefVersion":1,"typeDefDescription":"The direct parent-child relationship between attributes with an embedded type.","validStatusList":["ACTIVE","DELETED"]},"instanceProvenanceType":"CONTENT_PACK","metadataCollectionId":"2216ab62-176a-46c0-b889-9aa081754b54","createdBy":"Egeria","createTime":1632046251579,"version":1,"guid":"0a5b4abb-f1cd-46c3-bb29-2006e3620a5d","entityOneProxy":{"class":"EntityProxy","headerVersion":1,"type":{"class":"InstanceType","headerVersion":1,"typeDefCategory":"ENTITY_DEF","typeDefGUID":"ce7e72b8-396a-4013-8688-f9d973067425","typeDefName":"RelationalTable","typeDefVersion":1,"typeDefDescription":"A table within a relational database schema type.","typeDefSuperTypes":[{"headerVersion":1,"guid":"1a5e159b-913a-43b1-95fe-04433b25fca9","name":"SchemaAttribute","status":"ACTIVE_TYPEDEF"},{"headerVersion":1,"guid":"718d4244-8559-49ed-ad5a-10e5c305a656","name":"SchemaElement","status":"ACTIVE_TYPEDEF"},{"headerVersion":1,"guid":"a32316b8-dc8c-48c5-b12b-71c1b2a080bf","name":"Referenceable","status":"ACTIVE_TYPEDEF"},{"headerVersion":1,"guid":"4e7761e8-3969-4627-8f40-bfe3cde85a1d","name":"OpenMetadataRoot","status":"ACTIVE_TYPEDEF"}],"validStatusList":["ACTIVE","DELETED"],"validInstanceProperties":["aliases","defaultValueOverride","minimumLength","precision","length","orderedValues","allowsDuplicateValues","significantDigits","maxCardinality","cardinality","minCardinality","nativeClass","sortOrder","isNullable","name","position","isDeprecated","displayName","anchorGUID","description","qualifiedName","additionalProperties"]},"instanceProvenanceType":"CONTENT_PACK","metadataCollectionId":"2216ab62-176a-46c0-b889-9aa081754b54","createdBy":"Egeria","createTime":1632046251579,"version":1,"guid":"46fea469-ba83-496e-859d-963b4ae4101c","classifications":[{"class":"Classification","headerVersion":1,"type":{"class":"InstanceType","headerVersion":1,"typeDefCategory":"CLASSIFICATION_DEF","typeDefGUID":"e2bb76bb-774a-43ff-9045-3a05f663d5d9","typeDefName":"TypeEmbeddedAttribute","typeDefVersion":2,"typeDefDescription":"Type information embedded within an attribute.","validStatusList":["ACTIVE","DELETED"],"validInstanceProperties":["isDeprecated","qualifiedName","displayName","author","defaultValue","dataType","usage","description","schemaTypeName","versionNumber","fixedValue","encodingStandard","additionalProperties"]},"instanceProvenanceType":"CONTENT_PACK","metadataCollectionId":"2216ab62-176a-46c0-b889-9aa081754b54","createdBy":"Egeria","createTime":1632046251579,"version":1,"name":"TypeEmbeddedAttribute","properties":{"class":"InstanceProperties","headerVersion":0,"instanceProperties":{"length":{"class":"PrimitivePropertyValue","headerVersion":0,"instancePropertyCategory":"PRIMITIVE","typeGUID":"7fc49104-fd3a-46c8-b6bf-f16b6074cd35","typeName":"int","primitiveDefCategory":"OM_PRIMITIVE_TYPE_INT","primitiveValue":0},"schemaTypeName":{"class":"PrimitivePropertyValue","headerVersion":0,"instancePropertyCategory":"PRIMITIVE","typeGUID":"b34a64b9-554a-42b1-8f8a-7d5c2339f9c4","typeName":"string","primitiveDefCategory":"OM_PRIMITIVE_TYPE_STRING","primitiveValue":"RelationalTableType"}},"propertyCount":2,"propertyNames":["length","schemaTypeName"]},"status":"ACTIVE"}],"uniqueProperties":{"class":"InstanceProperties","headerVersion":0,"instanceProperties":{"qualifiedName":{"class":"PrimitivePropertyValue","headerVersion":0,"instancePropertyCategory":"PRIMITIVE","typeGUID":"b34a64b9-554a-42b1-8f8a-7d5c2339f9c4","typeName":"string","primitiveDefCategory":"OM_PRIMITIVE_TYPE_STRING","primitiveValue":"V37B8752.FH567.sys/BRANCH.RETAILSCHEMA.CUSTOMER"}},"propertyCount":1,"propertyNames":["qualifiedName"]},"status":"ACTIVE"},"entityTwoProxy":{"class":"EntityProxy","headerVersion":1,"type":{"class":"InstanceType","headerVersion":1,"typeDefCategory":"ENTITY_DEF","typeDefGUID":"aa8d5470-6dbc-4648-9e2f-045e5df9d2f9","typeDefName":"RelationalColumn","typeDefVersion":2,"typeDefDescription":"A column within a relational table.","typeDefSuperTypes":[{"headerVersion":1,"guid":"d81a0425-4e9b-4f31-bc1c-e18c3566da10","name":"TabularColumn","status":"ACTIVE_TYPEDEF"},{"headerVersion":1,"guid":"1a5e159b-913a-43b1-95fe-04433b25fca9","name":"SchemaAttribute","status":"ACTIVE_TYPEDEF"},{"headerVersion":1,"guid":"718d4244-8559-49ed-ad5a-10e5c305a656","name":"SchemaElement","status":"ACTIVE_TYPEDEF"},{"headerVersion":1,"guid":"a32316b8-dc8c-48c5-b12b-71c1b2a080bf","name":"Referenceable","status":"ACTIVE_TYPEDEF"},{"headerVersion":1,"guid":"4e7761e8-3969-4627-8f40-bfe3cde85a1d","name":"OpenMetadataRoot","status":"ACTIVE_TYPEDEF"}],"validStatusList":["ACTIVE","DELETED"],"validInstanceProperties":["isUnique","fraction","aliases","defaultValueOverride","minimumLength","precision","length","orderedValues","allowsDuplicateValues","significantDigits","maxCardinality","cardinality","minCardinality","nativeClass","sortOrder","isNullable","name","position","isDeprecated","displayName","anchorGUID","description","qualifiedName","additionalProperties"]},"instanceProvenanceType":"CONTENT_PACK","metadataCollectionId":"2216ab62-176a-46c0-b889-9aa081754b54","createdBy":"Egeria","createTime":1632046251579,"version":1,"guid":"35208ea5-84ff-429c-99c8-0321504a992b","classifications":[{"class":"Classification","headerVersion":1,"type":{"class":"InstanceType","headerVersion":1,"typeDefCategory":"CLASSIFICATION_DEF","typeDefGUID":"e2bb76bb-774a-43ff-9045-3a05f663d5d9","typeDefName":"TypeEmbeddedAttribute","typeDefVersion":2,"typeDefDescription":"Type information embedded within an attribute.","validStatusList":["ACTIVE","DELETED"],"validInstanceProperties":["isDeprecated","qualifiedName","displayName","author","defaultValue","dataType","usage","description","schemaTypeName","versionNumber","fixedValue","encodingStandard","additionalProperties"]},"instanceProvenanceType":"CONTENT_PACK","metadataCollectionId":"2216ab62-176a-46c0-b889-9aa081754b54","createdBy":"Egeria","createTime":1632046251579,"version":1,"name":"TypeEmbeddedAttribute","properties":{"class":"InstanceProperties","headerVersion":0,"instanceProperties":{"length":{"class":"PrimitivePropertyValue","headerVersion":0,"instancePropertyCategory":"PRIMITIVE","typeGUID":"7fc49104-fd3a-46c8-b6bf-f16b6074cd35","typeName":"int","primitiveDefCategory":"OM_PRIMITIVE_TYPE_INT","primitiveValue":12},"schemaTypeName":{"class":"PrimitivePropertyValue","headerVersion":0,"instancePropertyCategory":"PRIMITIVE","typeGUID":"b34a64b9-554a-42b1-8f8a-7d5c2339f9c4","typeName":"string","primitiveDefCategory":"OM_PRIMITIVE_TYPE_STRING","primitiveValue":"PrimitiveSchemaType"},"dataType":{"class":"PrimitivePropertyValue","headerVersion":0,"instancePropertyCategory":"PRIMITIVE","typeGUID":"b34a64b9-554a-42b1-8f8a-7d5c2339f9c4","typeName":"string","primitiveDefCategory":"OM_PRIMITIVE_TYPE_STRING","primitiveValue":"CHAR"}},"propertyCount":3,"propertyNames":["dataType","length","schemaTypeName"]},"status":"ACTIVE"}],"uniqueProperties":{"class":"InstanceProperties","headerVersion":0,"instanceProperties":{"qualifiedName":{"class":"PrimitivePropertyValue","headerVersion":0,"instancePropertyCategory":"PRIMITIVE","typeGUID":"b34a64b9-554a-42b1-8f8a-7d5c2339f9c4","typeName":"string","primitiveDefCategory":"OM_PRIMITIVE_TYPE_STRING","primitiveValue":"V37B8752.FH567.sys/BRANCH.RETAILSCHEMA.CUSTOMER.CUSTID"}},"propertyCount":1,"propertyNames":["qualifiedName"]},"status":"ACTIVE"},"status":"ACTIVE"},{"class":"Relationship","headerVersion":1,"type":{"class":"InstanceType","headerVersion":1,"typeDefCategory":"RELATIONSHIP_DEF","typeDefGUID":"0ffb9d87-7074-45da-a9b0-ae0859611133","typeDefName":"NestedSchemaAttribute","typeDefVersion":1,"typeDefDescription":"The direct parent-child relationship between attributes with an embedded type.","validStatusList":["ACTIVE","DELETED"]},"instanceProvenanceType":"CONTENT_PACK","metadataCollectionId":"2216ab62-176a-46c0-b889-9aa081754b54","createdBy":"Egeria","createTime":1632046251579,"version":1,"guid":"22b608f1-1d65-4962-a59b-690d5dd29a13","entityOneProxy":{"class":"EntityProxy","headerVersion":1,"type":{"class":"InstanceType","headerVersion":1,"typeDefCategory":"ENTITY_DEF","typeDefGUID":"ce7e72b8-396a-4013-8688-f9d973067425","typeDefName":"RelationalTable","typeDefVersion":1,"typeDefDescription":"A table within a relational database schema type.","typeDefSuperTypes":[{"headerVersion":1,"guid":"1a5e159b-913a-43b1-95fe-04433b25fca9","name":"SchemaAttribute","status":"ACTIVE_TYPEDEF"},{"headerVersion":1,"guid":"718d4244-8559-49ed-ad5a-10e5c305a656","name":"SchemaElement","status":"ACTIVE_TYPEDEF"},{"headerVersion":1,"guid":"a32316b8-dc8c-48c5-b12b-71c1b2a080bf","name":"Referenceable","status":"ACTIVE_TYPEDEF"},{"headerVersion":1,"guid":"4e7761e8-3969-4627-8f40-bfe3cde85a1d","name":"OpenMetadataRoot","status":"ACTIVE_TYPEDEF"}],"validStatusList":["ACTIVE","DELETED"],"validInstanceProperties":["aliases","defaultValueOverride","minimumLength","precision","length","orderedValues","allowsDuplicateValues","significantDigits","maxCardinality","cardinality","minCardinality","nativeClass","sortOrder","isNullable","name","position","isDeprecated","displayName","anchorGUID","description","qualifiedName","additionalProperties"]},"instanceProvenanceType":"CONTENT_PACK","metadataCollectionId":"2216ab62-176a-46c0-b889-9aa081754b54","createdBy":"Egeria","createTime":1632046251579,"version":1,"guid":"46fea469-ba83-496e-859d-963b4ae4101c","classifications":[{"class":"Classification","headerVersion":1,"type":{"class":"InstanceType","headerVersion":1,"typeDefCategory":"CLASSIFICATION_DEF","typeDefGUID":"e2bb76bb-774a-43ff-9045-3a05f663d5d9","typeDefName":"TypeEmbeddedAttribute","typeDefVersion":2,"typeDefDescription":"Type information embedded within an attribute.","validStatusList":["ACTIVE","DELETED"],"validInstanceProperties":["isDeprecated","qualifiedName","displayName","author","defaultValue","dataType","usage","description","schemaTypeName","versionNumber","fixedValue","encodingStandard","additionalProperties"]},"instanceProvenanceType":"CONTENT_PACK","metadataCollectionId":"2216ab62-176a-46c0-b889-9aa081754b54","createdBy":"Egeria","createTime":1632046251579,"version":1,"name":"TypeEmbeddedAttribute","properties":{"class":"InstanceProperties","headerVersion":0,"instanceProperties":{"length":{"class":"PrimitivePropertyValue","headerVersion":0,"instancePropertyCategory":"PRIMITIVE","typeGUID":"7fc49104-fd3a-46c8-b6bf-f16b6074cd35","typeName":"int","primitiveDefCategory":"OM_PRIMITIVE_TYPE_INT","primitiveValue":0},"schemaTypeName":{"class":"PrimitivePropertyValue","headerVersion":0,"instancePropertyCategory":"PRIMITIVE","typeGUID":"b34a64b9-554a-42b1-8f8a-7d5c2339f9c4","typeName":"string","primitiveDefCategory":"OM_PRIMITIVE_TYPE_STRING","primitiveValue":"RelationalTableType"}},"propertyCount":2,"propertyNames":["length","schemaTypeName"]},"status":"ACTIVE"}],"uniqueProperties":{"class":"InstanceProperties","headerVersion":0,"instanceProperties":{"qualifiedName":{"class":"PrimitivePropertyValue","headerVersion":0,"instancePropertyCategory":"PRIMITIVE","typeGUID":"b34a64b9-554a-42b1-8f8a-7d5c2339f9c4","typeName":"string","primitiveDefCategory":"OM_PRIMITIVE_TYPE_STRING","primitiveValue":"V37B8752.FH567.sys/BRANCH.RETAILSCHEMA.CUSTOMER"}},"propertyCount":1,"propertyNames":["qualifiedName"]},"status":"ACTIVE"},"entityTwoProxy":{"class":"EntityProxy","headerVersion":1,"type":{"class":"InstanceType","headerVersion":1,"typeDefCategory":"ENTITY_DEF","typeDefGUID":"aa8d5470-6dbc-4648-9e2f-045e5df9d2f9","typeDefName":"RelationalColumn","typeDefVersion":2,"typeDefDescription":"A column within a relational table.","typeDefSuperTypes":[{"headerVersion":1,"guid":"d81a0425-4e9b-4f31-bc1c-e18c3566da10","name":"TabularColumn","status":"ACTIVE_TYPEDEF"},{"headerVersion":1,"guid":"1a5e159b-913a-43b1-95fe-04433b25fca9","name":"SchemaAttribute","status":"ACTIVE_TYPEDEF"},{"headerVersion":1,"guid":"718d4244-8559-49ed-ad5a-10e5c305a656","name":"SchemaElement","status":"ACTIVE_TYPEDEF"},{"headerVersion":1,"guid":"a32316b8-dc8c-48c5-b12b-71c1b2a080bf","name":"Referenceable","status":"ACTIVE_TYPEDEF"},{"headerVersion":1,"guid":"4e7761e8-3969-4627-8f40-bfe3cde85a1d","name":"OpenMetadataRoot","status":"ACTIVE_TYPEDEF"}],"validStatusList":["ACTIVE","DELETED"],"validInstanceProperties":["isUnique","fraction","aliases","defaultValueOverride","minimumLength","precision","length","orderedValues","allowsDuplicateValues","significantDigits","maxCardinality","cardinality","minCardinality","nativeClass","sortOrder","isNullable","name","position","isDeprecated","displayName","anchorGUID","description","qualifiedName","additionalProperties"]},"instanceProvenanceType":"CONTENT_PACK","metadataCollectionId":"2216ab62-176a-46c0-b889-9aa081754b54","createdBy":"Egeria","createTime":1632046251579,"version":1,"guid":"95395f0d-cf4d-4c05-be42-908931b1d470","classifications":[{"class":"Classification","headerVersion":1,"type":{"class":"InstanceType","headerVersion":1,"typeDefCategory":"CLASSIFICATION_DEF","typeDefGUID":"e2bb76bb-774a-43ff-9045-3a05f663d5d9","typeDefName":"TypeEmbeddedAttribute","typeDefVersion":2,"typeDefDescription":"Type information embedded within an attribute.","validStatusList":["ACTIVE","DELETED"],"validInstanceProperties":["isDeprecated","qualifiedName","displayName","author","defaultValue","dataType","usage","description","schemaTypeName","versionNumber","fixedValue","encodingStandard","additionalProperties"]},"instanceProvenanceType":"CONTENT_PACK","metadataCollectionId":"2216ab62-176a-46c0-b889-9aa081754b54","createdBy":"Egeria","createTime":1632046251579,"version":1,"name":"TypeEmbeddedAttribute","properties":{"class":"InstanceProperties","headerVersion":0,"instanceProperties":{"length":{"class":"PrimitivePropertyValue","headerVersion":0,"instancePropertyCategory":"PRIMITIVE","typeGUID":"7fc49104-fd3a-46c8-b6bf-f16b6074cd35","typeName":"int","primitiveDefCategory":"OM_PRIMITIVE_TYPE_INT","primitiveValue":40},"schemaTypeName":{"class":"PrimitivePropertyValue","headerVersion":0,"instancePropertyCategory":"PRIMITIVE","typeGUID":"b34a64b9-554a-42b1-8f8a-7d5c2339f9c4","typeName":"string","primitiveDefCategory":"OM_PRIMITIVE_TYPE_STRING","primitiveValue":"PrimitiveSchemaType"},"dataType":{"class":"PrimitivePropertyValue","headerVersion":0,"instancePropertyCategory":"PRIMITIVE","typeGUID":"b34a64b9-554a-42b1-8f8a-7d5c2339f9c4","typeName":"string","primitiveDefCategory":"OM_PRIMITIVE_TYPE_STRING","primitiveValue":"CHAR"}},"propertyCount":3,"propertyNames":["dataType","length","schemaTypeName"]},"status":"ACTIVE"}],"uniqueProperties":{"class":"InstanceProperties","headerVersion":0,"instanceProperties":{"qualifiedName":{"class":"PrimitivePropertyValue","headerVersion":0,"instancePropertyCategory":"PRIMITIVE","typeGUID":"b34a64b9-554a-42b1-8f8a-7d5c2339f9c4","typeName":"string","primitiveDefCategory":"OM_PRIMITIVE_TYPE_STRING","primitiveValue":"V37B8752.FH567.sys/BRANCH.RETAILSCHEMA.CUSTOMER.CUSTNAME"}},"propertyCount":1,"propertyNames":["qualifiedName"]},"status":"ACTIVE"},"status":"ACTIVE"},{"class":"Relationship","headerVersion":1,"type":{"class":"InstanceType","headerVersion":1,"typeDefCategory":"RELATIONSHIP_DEF","typeDefGUID":"0ffb9d87-7074-45da-a9b0-ae0859611133","typeDefName":"NestedSchemaAttribute","typeDefVersion":1,"typeDefDescription":"The direct parent-child relationship between attributes with an embedded type.","validStatusList":["ACTIVE","DELETED"]},"instanceProvenanceType":"CONTENT_PACK","metadataCollectionId":"2216ab62-176a-46c0-b889-9aa081754b54","createdBy":"Egeria","createTime":1632046251579,"version":1,"guid":"cb57ac14-0b8d-4e30-931e-b0e0adf26fe3","entityOneProxy":{"class":"EntityProxy","headerVersion":1,"type":{"class":"InstanceType","headerVersion":1,"typeDefCategory":"ENTITY_DEF","typeDefGUID":"ce7e72b8-396a-4013-8688-f9d973067425","typeDefName":"RelationalTable","typeDefVersion":1,"typeDefDescription":"A table within a relational database schema type.","typeDefSuperTypes":[{"headerVersion":1,"guid":"1a5e159b-913a-43b1-95fe-04433b25fca9","name":"SchemaAttribute","status":"ACTIVE_TYPEDEF"},{"headerVersion":1,"guid":"718d4244-8559-49ed-ad5a-10e5c305a656","name":"SchemaElement","status":"ACTIVE_TYPEDEF"},{"headerVersion":1,"guid":"a32316b8-dc8c-48c5-b12b-71c1b2a080bf","name":"Referenceable","status":"ACTIVE_TYPEDEF"},{"headerVersion":1,"guid":"4e7761e8-3969-4627-8f40-bfe3cde85a1d","name":"OpenMetadataRoot","status":"ACTIVE_TYPEDEF"}],"validStatusList":["ACTIVE","DELETED"],"validInstanceProperties":["aliases","defaultValueOverride","minimumLength","precision","length","orderedValues","allowsDuplicateValues","significantDigits","maxCardinality","cardinality","minCardinality","nativeClass","sortOrder","isNullable","name","position","isDeprecated","displayName","anchorGUID","description","qualifiedName","additionalProperties"]},"instanceProvenanceType":"CONTENT_PACK","metadataCollectionId":"2216ab62-176a-46c0-b889-9aa081754b54","createdBy":"Egeria","createTime":1632046251579,"version":1,"guid":"46fea469-ba83-496e-859d-963b4ae4101c","classifications":[{"class":"Classification","headerVersion":1,"type":{"class":"InstanceType","headerVersion":1,"typeDefCategory":"CLASSIFICATION_DEF","typeDefGUID":"e2bb76bb-774a-43ff-9045-3a05f663d5d9","typeDefName":"TypeEmbeddedAttribute","typeDefVersion":2,"typeDefDescription":"Type information embedded within an attribute.","validStatusList":["ACTIVE","DELETED"],"validInstanceProperties":["isDeprecated","qualifiedName","displayName","author","defaultValue","dataType","usage","description","schemaTypeName","versionNumber","fixedValue","encodingStandard","additionalProperties"]},"instanceProvenanceType":"CONTENT_PACK","metadataCollectionId":"2216ab62-176a-46c0-b889-9aa081754b54","createdBy":"Egeria","createTime":1632046251579,"version":1,"name":"TypeEmbeddedAttribute","properties":{"class":"InstanceProperties","headerVersion":0,"instanceProperties":{"length":{"class":"PrimitivePropertyValue","headerVersion":0,"instancePropertyCategory":"PRIMITIVE","typeGUID":"7fc49104-fd3a-46c8-b6bf-f16b6074cd35","typeName":"int","primitiveDefCategory":"OM_PRIMITIVE_TYPE_INT","primitiveValue":0},"schemaTypeName":{"class":"PrimitivePropertyValue","headerVersion":0,"instancePropertyCategory":"PRIMITIVE","typeGUID":"b34a64b9-554a-42b1-8f8a-7d5c2339f9c4","typeName":"string","primitiveDefCategory":"OM_PRIMITIVE_TYPE_STRING","primitiveValue":"RelationalTableType"}},"propertyCount":2,"propertyNames":["length","schemaTypeName"]},"status":"ACTIVE"}],"uniqueProperties":{"class":"InstanceProperties","headerVersion":0,"instanceProperties":{"qualifiedName":{"class":"PrimitivePropertyValue","headerVersion":0,"instancePropertyCategory":"PRIMITIVE","typeGUID":"b34a64b9-554a-42b1-8f8a-7d5c2339f9c4","typeName":"string","primitiveDefCategory":"OM_PRIMITIVE_TYPE_STRING","primitiveValue":"V37B8752.FH567.sys/BRANCH.RETAILSCHEMA.CUSTOMER"}},"propertyCount":1,"propertyNames":["qualifiedName"]},"status":"ACTIVE"},"entityTwoProxy":{"class":"EntityProxy","headerVersion":1,"type":{"class":"InstanceType","headerVersion":1,"typeDefCategory":"ENTITY_DEF","typeDefGUID":"aa8d5470-6dbc-4648-9e2f-045e5df9d2f9","typeDefName":"RelationalColumn","typeDefVersion":2,"typeDefDescription":"A column within a relational table.","typeDefSuperTypes":[{"headerVersion":1,"guid":"d81a0425-4e9b-4f31-bc1c-e18c3566da10","name":"TabularColumn","status":"ACTIVE_TYPEDEF"},{"headerVersion":1,"guid":"1a5e159b-913a-43b1-95fe-04433b25fca9","name":"SchemaAttribute","status":"ACTIVE_TYPEDEF"},{"headerVersion":1,"guid":"718d4244-8559-49ed-ad5a-10e5c305a656","name":"SchemaElement","status":"ACTIVE_TYPEDEF"},{"headerVersion":1,"guid":"a32316b8-dc8c-48c5-b12b-71c1b2a080bf","name":"Referenceable","status":"ACTIVE_TYPEDEF"},{"headerVersion":1,"guid":"4e7761e8-3969-4627-8f40-bfe3cde85a1d","name":"OpenMetadataRoot","status":"ACTIVE_TYPEDEF"}],"validStatusList":["ACTIVE","DELETED"],"validInstanceProperties":["isUnique","fraction","aliases","defaultValueOverride","minimumLength","precision","length","orderedValues","allowsDuplicateValues","significantDigits","maxCardinality","cardinality","minCardinality","nativeClass","sortOrder","isNullable","name","position","isDeprecated","displayName","anchorGUID","description","qualifiedName","additionalProperties"]},"instanceProvenanceType":"CONTENT_PACK","metadataCollectionId":"2216ab62-176a-46c0-b889-9aa081754b54","createdBy":"Egeria","createTime":1632046251579,"version":1,"guid":"b3bfe44e-5b40-4c7a-b770-4b9f8f4be9b3","classifications":[{"class":"Classification","headerVersion":1,"type":{"class":"InstanceType","headerVersion":1,"typeDefCategory":"CLASSIFICATION_DEF","typeDefGUID":"e2bb76bb-774a-43ff-9045-3a05f663d5d9","typeDefName":"TypeEmbeddedAttribute","typeDefVersion":2,"typeDefDescription":"Type information embedded within an attribute.","validStatusList":["ACTIVE","DELETED"],"validInstanceProperties":["isDeprecated","qualifiedName","displayName","author","defaultValue","dataType","usage","description","schemaTypeName","versionNumber","fixedValue","encodingStandard","additionalProperties"]},"instanceProvenanceType":"CONTENT_PACK","metadataCollectionId":"2216ab62-176a-46c0-b889-9aa081754b54","createdBy":"Egeria","createTime":1632046251579,"version":1,"name":"TypeEmbeddedAttribute","properties":{"class":"InstanceProperties","headerVersion":0,"instanceProperties":{"length":{"class":"PrimitivePropertyValue","headerVersion":0,"instancePropertyCategory":"PRIMITIVE","typeGUID":"7fc49104-fd3a-46c8-b6bf-f16b6074cd35","typeName":"int","primitiveDefCategory":"OM_PRIMITIVE_TYPE_INT","primitiveValue":10},"schemaTypeName":{"class":"PrimitivePropertyValue","headerVersion":0,"instancePropertyCategory":"PRIMITIVE","typeGUID":"b34a64b9-554a-42b1-8f8a-7d5c2339f9c4","typeName":"string","primitiveDefCategory":"OM_PRIMITIVE_TYPE_STRING","primitiveValue":"PrimitiveSchemaType"},"dataType":{"class":"PrimitivePropertyValue","headerVersion":0,"instancePropertyCategory":"PRIMITIVE","typeGUID":"b34a64b9-554a-42b1-8f8a-7d5c2339f9c4","typeName":"string","primitiveDefCategory":"OM_PRIMITIVE_TYPE_STRING","primitiveValue":"CHAR"}},"propertyCount":3,"propertyNames":["dataType","length","schemaTypeName"]},"status":"ACTIVE"}],"uniqueProperties":{"class":"InstanceProperties","headerVersion":0,"instanceProperties":{"qualifiedName":{"class":"PrimitivePropertyValue","headerVersion":0,"instancePropertyCategory":"PRIMITIVE","typeGUID":"b34a64b9-554a-42b1-8f8a-7d5c2339f9c4","typeName":"string","primitiveDefCategory":"OM_PRIMITIVE_TYPE_STRING","primitiveValue":"V37B8752.FH567.sys/BRANCH.RETAILSCHEMA.CUSTOMER.CUSTSTATUS"}},"propertyCount":1,"propertyNames":["qualifiedName"]},"status":"ACTIVE"},"status":"ACTIVE"},{"class":"Relationship","headerVersion":1,"type":{"class":"InstanceType","headerVersion":1,"typeDefCategory":"RELATIONSHIP_DEF","typeDefGUID":"0ffb9d87-7074-45da-a9b0-ae0859611133","typeDefName":"NestedSchemaAttribute","typeDefVersion":1,"typeDefDescription":"The direct parent-child relationship between attributes with an embedded type.","validStatusList":["ACTIVE","DELETED"]},"instanceProvenanceType":"CONTENT_PACK","metadataCollectionId":"2216ab62-176a-46c0-b889-9aa081754b54","createdBy":"Egeria","createTime":1632046251579,"version":1,"guid":"96800906-fb92-4481-a89b-2016a4875811","entityOneProxy":{"class":"EntityProxy","headerVersion":1,"type":{"class":"InstanceType","headerVersion":1,"typeDefCategory":"ENTITY_DEF","typeDefGUID":"ce7e72b8-396a-4013-8688-f9d973067425","typeDefName":"RelationalTable","typeDefVersion":1,"typeDefDescription":"A table within a relational database schema type.","typeDefSuperTypes":[{"headerVersion":1,"guid":"1a5e159b-913a-43b1-95fe-04433b25fca9","name":"SchemaAttribute","status":"ACTIVE_TYPEDEF"},{"headerVersion":1,"guid":"718d4244-8559-49ed-ad5a-10e5c305a656","name":"SchemaElement","status":"ACTIVE_TYPEDEF"},{"headerVersion":1,"guid":"a32316b8-dc8c-48c5-b12b-71c1b2a080bf","name":"Referenceable","status":"ACTIVE_TYPEDEF"},{"headerVersion":1,"guid":"4e7761e8-3969-4627-8f40-bfe3cde85a1d","name":"OpenMetadataRoot","status":"ACTIVE_TYPEDEF"}],"validStatusList":["ACTIVE","DELETED"],"validInstanceProperties":["aliases","defaultValueOverride","minimumLength","precision","length","orderedValues","allowsDuplicateValues","significantDigits","maxCardinality","cardinality","minCardinality","nativeClass","sortOrder","isNullable","name","position","isDeprecated","displayName","anchorGUID","description","qualifiedName","additionalProperties"]},"instanceProvenanceType":"CONTENT_PACK","metadataCollectionId":"2216ab62-176a-46c0-b889-9aa081754b54","createdBy":"Egeria","createTime":1632046251579,"version":1,"guid":"46fea469-ba83-496e-859d-963b4ae4101c","classifications":[{"class":"Classification","headerVersion":1,"type":{"class":"InstanceType","headerVersion":1,"typeDefCategory":"CLASSIFICATION_DEF","typeDefGUID":"e2bb76bb-774a-43ff-9045-3a05f663d5d9","typeDefName":"TypeEmbeddedAttribute","typeDefVersion":2,"typeDefDescription":"Type information embedded within an attribute.","validStatusList":["ACTIVE","DELETED"],"validInstanceProperties":["isDeprecated","qualifiedName","displayName","author","defaultValue","dataType","usage","description","schemaTypeName","versionNumber","fixedValue","encodingStandard","additionalProperties"]},"instanceProvenanceType":"CONTENT_PACK","metadataCollectionId":"2216ab62-176a-46c0-b889-9aa081754b54","createdBy":"Egeria","createTime":1632046251579,"version":1,"name":"TypeEmbeddedAttribute","properties":{"class":"InstanceProperties","headerVersion":0,"instanceProperties":{"length":{"class":"PrimitivePropertyValue","headerVersion":0,"instancePropertyCategory":"PRIMITIVE","typeGUID":"7fc49104-fd3a-46c8-b6bf-f16b6074cd35","typeName":"int","primitiveDefCategory":"OM_PRIMITIVE_TYPE_INT","primitiveValue":0},"schemaTypeName":{"class":"PrimitivePropertyValue","headerVersion":0,"instancePropertyCategory":"PRIMITIVE","typeGUID":"b34a64b9-554a-42b1-8f8a-7d5c2339f9c4","typeName":"string","primitiveDefCategory":"OM_PRIMITIVE_TYPE_STRING","primitiveValue":"RelationalTableType"}},"propertyCount":2,"propertyNames":["length","schemaTypeName"]},"status":"ACTIVE"}],"uniqueProperties":{"class":"InstanceProperties","headerVersion":0,"instanceProperties":{"qualifiedName":{"class":"PrimitivePropertyValue","headerVersion":0,"instancePropertyCategory":"PRIMITIVE","typeGUID":"b34a64b9-554a-42b1-8f8a-7d5c2339f9c4","typeName":"string","primitiveDefCategory":"OM_PRIMITIVE_TYPE_STRING","primitiveValue":"V37B8752.FH567.sys/BRANCH.RETAILSCHEMA.CUSTOMER"}},"propertyCount":1,"propertyNames":["qualifiedName"]},"status":"ACTIVE"},"entityTwoProxy":{"class":"EntityProxy","headerVersion":1,"type":{"class":"InstanceType","headerVersion":1,"typeDefCategory":"ENTITY_DEF","typeDefGUID":"aa8d5470-6dbc-4648-9e2f-045e5df9d2f9","typeDefName":"RelationalColumn","typeDefVersion":2,"typeDefDescription":"A column within a relational table.","typeDefSuperTypes":[{"headerVersion":1,"guid":"d81a0425-4e9b-4f31-bc1c-e18c3566da10","name":"TabularColumn","status":"ACTIVE_TYPEDEF"},{"headerVersion":1,"guid":"1a5e159b-913a-43b1-95fe-04433b25fca9","name":"SchemaAttribute","status":"ACTIVE_TYPEDEF"},{"headerVersion":1,"guid":"718d4244-8559-49ed-ad5a-10e5c305a656","name":"SchemaElement","status":"ACTIVE_TYPEDEF"},{"headerVersion":1,"guid":"a32316b8-dc8c-48c5-b12b-71c1b2a080bf","name":"Referenceable","status":"ACTIVE_TYPEDEF"},{"headerVersion":1,"guid":"4e7761e8-3969-4627-8f40-bfe3cde85a1d","name":"OpenMetadataRoot","status":"ACTIVE_TYPEDEF"}],"validStatusList":["ACTIVE","DELETED"],"validInstanceProperties":["isUnique","fraction","aliases","defaultValueOverride","minimumLength","precision","length","orderedValues","allowsDuplicateValues","significantDigits","maxCardinality","cardinality","minCardinality","nativeClass","sortOrder","isNullable","name","position","isDeprecated","displayName","anchorGUID","description","qualifiedName","additionalProperties"]},"instanceProvenanceType":"CONTENT_PACK","metadataCollectionId":"2216ab62-176a-46c0-b889-9aa081754b54","createdBy":"Egeria","createTime":1632046251579,"version":1,"guid":"acfcae4c-f1a8-42dc-ac7d-28e56516721c","classifications":[{"class":"Classification","headerVersion":1,"type":{"class":"InstanceType","headerVersion":1,"typeDefCategory":"CLASSIFICATION_DEF","typeDefGUID":"e2bb76bb-774a-43ff-9045-3a05f663d5d9","typeDefName":"TypeEmbeddedAttribute","typeDefVersion":2,"typeDefDescription":"Type information embedded within an attribute.","validStatusList":["ACTIVE","DELETED"],"validInstanceProperties":["isDeprecated","qualifiedName","displayName","author","defaultValue","dataType","usage","description","schemaTypeName","versionNumber","fixedValue","encodingStandard","additionalProperties"]},"instanceProvenanceType":"CONTENT_PACK","metadataCollectionId":"2216ab62-176a-46c0-b889-9aa081754b54","createdBy":"Egeria","createTime":1632046251579,"version":1,"name":"TypeEmbeddedAttribute","properties":{"class":"InstanceProperties","headerVersion":0,"instanceProperties":{"length":{"class":"PrimitivePropertyValue","headerVersion":0,"instancePropertyCategory":"PRIMITIVE","typeGUID":"7fc49104-fd3a-46c8-b6bf-f16b6074cd35","typeName":"int","primitiveDefCategory":"OM_PRIMITIVE_TYPE_INT","primitiveValue":10},"schemaTypeName":{"class":"PrimitivePropertyValue","headerVersion":0,"instancePropertyCategory":"PRIMITIVE","typeGUID":"b34a64b9-554a-42b1-8f8a-7d5c2339f9c4","typeName":"string","primitiveDefCategory":"OM_PRIMITIVE_TYPE_STRING","primitiveValue":"PrimitiveSchemaType"},"dataType":{"class":"PrimitivePropertyValue","headerVersion":0,"instancePropertyCategory":"PRIMITIVE","typeGUID":"b34a64b9-554a-42b1-8f8a-7d5c2339f9c4","typeName":"string","primitiveDefCategory":"OM_PRIMITIVE_TYPE_STRING","primitiveValue":"CHAR"}},"propertyCount":3,"propertyNames":["dataType","length","schemaTypeName"]},"status":"ACTIVE"}],"uniqueProperties":{"class":"InstanceProperties","headerVersion":0,"instanceProperties":{"qualifiedName":{"class":"PrimitivePropertyValue","headerVersion":0,"instancePropertyCategory":"PRIMITIVE","typeGUID":"b34a64b9-554a-42b1-8f8a-7d5c2339f9c4","typeName":"string","primitiveDefCategory":"OM_PRIMITIVE_TYPE_STRING","primitiveValue":"V37B8752.FH567.sys/BRANCH.RETAILSCHEMA.CUSTOMER.CUSTCARD"}},"propertyCount":1,"propertyNames":["qualifiedName"]},"status":"ACTIVE"},"status":"ACTIVE"}]}}